django_nextflow/__init__.py
django_nextflow/graphs.py
django_nextflow/models.py
django_nextflow/utils.py
django_nextflow/migrations/0001_initial.py
django_nextflow/migrations/0002_pipelinecategory_alter_pipeline_options_and_more.py
django_nextflow/migrations/0003_data_is_binary.py
django_nextflow/migrations/0004_execution_data_params_execution_execution_params_and_more.py
django_nextflow/migrations/__init__.py
django_nextflow-0.12.1.dist-info/LICENSE
django_nextflow-0.12.1.dist-info/METADATA
django_nextflow-0.12.1.dist-info/WHEEL
django_nextflow-0.12.1.dist-info/top_level.txt
django_nextflow-0.12.1.dist-info/RECORD
